skyline_console/__init__.py
skyline_console/__main__.py
skyline_console/py.typed
skyline_console/version.py
skyline_console/static/Container.bundle.1663167892.js
skyline_console/static/Container.bundle.1663167892.js.gz
skyline_console/static/auth.bundle.1663167892.js
skyline_console/static/auth.bundle.1663167892.js.gz
skyline_console/static/base.bundle.1663167892.js
skyline_console/static/base.bundle.1663167892.js.gz
skyline_console/static/basic.bundle.1663167892.js
skyline_console/static/basic.bundle.1663167892.js.gz
skyline_console/static/common.bundle.1663167892.js
skyline_console/static/common.bundle.1663167892.js.gz
skyline_console/static/compute.bundle.1663167892.js
skyline_console/static/compute.bundle.1663167892.js.gz
skyline_console/static/configuration.bundle.1663167892.js
skyline_console/static/configuration.bundle.1663167892.js.gz
skyline_console/static/container-infra.bundle.1663167892.js
skyline_console/static/container-infra.bundle.1663167892.js.gz
skyline_console/static/f7186078e00d958aa2b316483dfc7e1c.js
skyline_console/static/f7186078e00d958aa2b316483dfc7e1c.js.gz
skyline_console/static/favicon.ico
skyline_console/static/heat.bundle.1663167892.js
skyline_console/static/heat.bundle.1663167892.js.gz
skyline_console/static/identity.bundle.1663167892.js
skyline_console/static/identity.bundle.1663167892.js.gz
skyline_console/static/index.html
skyline_console/static/main.bundle.1663167892.js
skyline_console/static/main.bundle.1663167892.js.gz
skyline_console/static/management.bundle.1663167892.js
skyline_console/static/monitor-center.bundle.1663167892.js
skyline_console/static/monitor-center.bundle.1663167892.js.gz
skyline_console/static/network.bundle.1663167892.js
skyline_console/static/network.bundle.1663167892.js.gz
skyline_console/static/runtime.1663167892.js
skyline_console/static/share.bundle.1663167892.js
skyline_console/static/share.bundle.1663167892.js.gz
skyline_console/static/storage.bundle.1663167892.js
skyline_console-7.0.0.dist-info/AUTHORS
skyline_console-7.0.0.dist-info/LICENSE
skyline_console-7.0.0.dist-info/METADATA
skyline_console-7.0.0.dist-info/WHEEL
skyline_console-7.0.0.dist-info/pbr.json
skyline_console-7.0.0.dist-info/top_level.txt
skyline_console-7.0.0.dist-info/RECORD
