Metadata-Version: 2.1
Name: skyline-console
Version: 7.0.0
Summary: OpenStack Skyline Console
Home-page: https://docs.openstack.org/skyline-console/latest/
Author: OpenStack
Author-email: openstack-discuss@lists.openstack.org
Project-URL: Source, https://opendev.org/openstack/skyline-console
Project-URL: Tracker, https://bugs.launchpad.net/skyline-console
Classifier: Environment :: OpenStack
Classifier: Intended Audience :: Information Technology
Classifier: Intended Audience :: System Administrators
Classifier: License :: OSI Approved :: Apache Software License
Classifier: Operating System :: POSIX :: Linux
Classifier: Programming Language :: Python
Classifier: Programming Language :: Python :: Implementation :: CPython
Classifier: Programming Language :: Python :: 3 :: Only
Classifier: Programming Language :: Python :: 3
Classifier: Programming Language :: Python :: 3.8
Classifier: Programming Language :: Python :: 3.9
Requires-Python: >=3.8
License-File: LICENSE
License-File: AUTHORS
Requires-Dist: pbr >=5.8.0
